{
  "collectionName": "components_objects_delivery_addresses",
  "info": {
    "displayName": "delivery-address"
  },
  "options": {},
  "attributes": {
    "city": {
      "type": "string",
      "required": true
    },
    "street": {
      "type": "string",
      "required": true
    },
    "house": {
      "type": "string",
      "required": true
    },
    "entrance": {
      "type": "string"
    },
    "apartment": {
      "type": "string"
    },
    "floor": {
      "type": "string"
    }
  }
}
